aliyunsdkopenanalytics_open/__init__.py
aliyunsdkopenanalytics_open/endpoint.py
aliyunsdkopenanalytics_open/request/__init__.py
aliyunsdkopenanalytics_open/request/v20180619/AddAccountRequest.py
aliyunsdkopenanalytics_open/request/v20180619/AddEndPointRequest.py
aliyunsdkopenanalytics_open/request/v20180619/CancelQueryByExecuteIdRequest.py
aliyunsdkopenanalytics_open/request/v20180619/CancelQueryByIdRequest.py
aliyunsdkopenanalytics_open/request/v20180619/CancelSparkStatementRequest.py
aliyunsdkopenanalytics_open/request/v20180619/CheckWorkloadSchemaPrefixExistsRequest.py
aliyunsdkopenanalytics_open/request/v20180619/CreateInstanceRequest.py
aliyunsdkopenanalytics_open/request/v20180619/CreateLakehouseRequest.py
aliyunsdkopenanalytics_open/request/v20180619/CreateLakehouseWorkloadRequest.py
aliyunsdkopenanalytics_open/request/v20180619/DeleteAccountRequest.py
aliyunsdkopenanalytics_open/request/v20180619/DescribeTagsRequest.py
aliyunsdkopenanalytics_open/request/v20180619/DumpLakehouseWorkloadRequest.py
aliyunsdkopenanalytics_open/request/v20180619/ExecuteSparkStatementRequest.py
aliyunsdkopenanalytics_open/request/v20180619/GetAllowIPRequest.py
aliyunsdkopenanalytics_open/request/v20180619/GetEndPointByDomainRequest.py
aliyunsdkopenanalytics_open/request/v20180619/GetEndPointRequest.py
aliyunsdkopenanalytics_open/request/v20180619/GetJobAttemptLogRequest.py
aliyunsdkopenanalytics_open/request/v20180619/GetJobDetailRequest.py
aliyunsdkopenanalytics_open/request/v20180619/GetJobLogRequest.py
aliyunsdkopenanalytics_open/request/v20180619/GetJobStatusRequest.py
aliyunsdkopenanalytics_open/request/v20180619/GetLakehouseWorkloadMonitorInfoRequest.py
aliyunsdkopenanalytics_open/request/v20180619/GetPolarDbInstanceRequest.py
aliyunsdkopenanalytics_open/request/v20180619/GetRdsInstanceRequest.py
aliyunsdkopenanalytics_open/request/v20180619/GetSparkSessionStateRequest.py
aliyunsdkopenanalytics_open/request/v20180619/GetSparkStatementRequest.py
aliyun_python_sdk_openanalytics_open-2.0.5.dist-info/LICENSE
aliyun_python_sdk_openanalytics_open-2.0.5.dist-info/METADATA
aliyun_python_sdk_openanalytics_open-2.0.5.dist-info/WHEEL
aliyun_python_sdk_openanalytics_open-2.0.5.dist-info/top_level.txt
aliyun_python_sdk_openanalytics_open-2.0.5.dist-info/RECORD
